{
  "volume": 1,
  "weight": 150,
  "agingSpeed": 254,
  "objectAfterRot": "illarion:item_2302",
  "script": "item.general.metal",
  "rotsInInventory": false,
  "brightness": 0,
  "worth": 13500,
  "buyStack": 1,
  "maxStack": 1,
  "rareness": 1,
  "name": "gynkeseMercenarysHelmet",
  "level": 70,
  "armor": {
    "bodyParts": 1,
    "puncture": 37,
    "stroke": 73,
    "thrust": 55,
    "magicDisturbance": 0,
    "absorb": 0,
    "stiffness": 0,
    "type": 3
  },
  "visual": "illarion:items/item_2302",
  "metadata": {
    "id": 2302
  }
}