{
  "volume": 1,
  "weight": 130,
  "agingSpeed": 254,
  "objectAfterRot": "illarion:item_1459",
  "script": "item.general.cloth",
  "rotsInInventory": false,
  "brightness": 0,
  "worth": 32500,
  "buyStack": 1,
  "maxStack": 1,
  "rareness": 1,
  "name": "rangersGloves",
  "level": 100,
  "armor": {
    "bodyParts": 8,
    "puncture": 75,
    "stroke": 50,
    "thrust": 100,
    "magicDisturbance": 0,
    "absorb": 0,
    "stiffness": 0,
    "type": 2
  },
  "visual": "illarion:items/item_1459",
  "metadata": {
    "id": 1459
  }
}