{
  "volume": 1,
  "weight": 150,
  "agingSpeed": 254,
  "objectAfterRot": "illarion:item_7",
  "script": "item.general.metal",
  "rotsInInventory": false,
  "brightness": 0,
  "worth": 1200,
  "buyStack": 1,
  "maxStack": 1,
  "rareness": 1,
  "name": "hornedHelmet",
  "level": 20,
  "armor": {
    "bodyParts": 1,
    "puncture": 21,
    "stroke": 14,
    "thrust": 28,
    "magicDisturbance": 0,
    "absorb": 0,
    "stiffness": 0,
    "type": 2
  },
  "visual": "illarion:items/item_7",
  "metadata": {
    "id": 7
  }
}