{
  "race": "illarion:race_58",
  "hitpoints": 10000,
  "movementType": "walk",
  "canAttack": true,
  "canHealSelf": false,
  "script": "monster.race_58_dog.default",
  "minSize": 90,
  "maxSize": 100,
  "attributes": {
    "strength": {
      "min": 1,
      "max": 3
    },
    "constitution": {
      "min": 1,
      "max": 3
    },
    "dexterity": {
      "min": 1,
      "max": 3
    },
    "agility": {
      "min": 1,
      "max": 3
    },
    "intelligence": {
      "min": 1,
      "max": 3
    },
    "willpower": {
      "min": 1,
      "max": 3
    },
    "perception": {
      "min": 1,
      "max": 3
    },
    "essence": {
      "min": 1,
      "max": 3
    }
  },
  "skills": {
    "illarion:skill_21": {
      "min": 10,
      "max": 20
    },
    "illarion:skill_27": {
      "min": 10,
      "max": 20
    },
    "illarion:skill_26": {
      "min": 10,
      "max": 20
    },
    "illarion:skill_28": {
      "min": 10,
      "max": 20
    },
    "illarion:skill_29": {
      "min": 10,
      "max": 20
    },
    "illarion:skill_25": {
      "min": 10,
      "max": 20
    },
    "illarion:skill_23": {
      "min": 10,
      "max": 20
    },
    "illarion:skill_24": {
      "min": 10,
      "max": 20
    },
    "illarion:skill_22": {
      "min": 10,
      "max": 20
    },
    "illarion:skill_37": {
      "min": 10,
      "max": 20
    }
  },
  "items": {
    "breast": {
      "item": "illarion:item_182",
      "minCount": 1,
      "maxCount": 1
    }
  },
  "drops": {
    "1": {
      "1717": {
        "chance": 0.5,
        "minCount": 1,
        "maxCount": 1,
        "minQuality": 3,
        "maxQuality": 3,
        "minDurability": 33,
        "maxDurability": 33,
        "item": "illarion:item_63"
      }
    },
    "2": {
      "1718": {
        "chance": 1,
        "minCount": 1,
        "maxCount": 1,
        "minQuality": 3,
        "maxQuality": 3,
        "minDurability": 33,
        "maxDurability": 33,
        "item": "illarion:item_2586"
      }
    }
  },
  "metadata": {
    "id": 582
  }
}