{
  "race": "illarion:race_19",
  "hitpoints": 10000,
  "movementType": "walk",
  "canAttack": true,
  "canHealSelf": false,
  "script": "monster.race_26_transparent_spider.default",
  "minSize": 80,
  "maxSize": 100,
  "attributes": {
    "strength": {
      "min": 25,
      "max": 33
    },
    "constitution": {
      "min": 25,
      "max": 33
    },
    "dexterity": {
      "min": 25,
      "max": 33
    },
    "agility": {
      "min": 25,
      "max": 33
    },
    "intelligence": {
      "min": 25,
      "max": 33
    },
    "perception": {
      "min": 25,
      "max": 33
    },
    "essence": {
      "min": 25,
      "max": 33
    },
    "willpower": {
      "min": 28,
      "max": 32
    }
  },
  "skills": {
    "illarion:skill_21": {
      "min": 70,
      "max": 80
    },
    "illarion:skill_27": {
      "min": 70,
      "max": 80
    },
    "illarion:skill_26": {
      "min": 70,
      "max": 80
    },
    "illarion:skill_28": {
      "min": 70,
      "max": 80
    },
    "illarion:skill_29": {
      "min": 70,
      "max": 80
    },
    "illarion:skill_25": {
      "min": 70,
      "max": 80
    },
    "illarion:skill_23": {
      "min": 70,
      "max": 80
    },
    "illarion:skill_24": {
      "min": 70,
      "max": 80
    },
    "illarion:skill_22": {
      "min": 70,
      "max": 80
    },
    "illarion:skill_37": {
      "min": 70,
      "max": 80
    }
  },
  "items": {
    "head": {
      "item": "illarion:item_2303",
      "minCount": 1,
      "maxCount": 1
    },
    "breast": {
      "item": "illarion:item_2393",
      "minCount": 1,
      "maxCount": 1
    },
    "right hand": {
      "item": "illarion:item_297",
      "minCount": 1,
      "maxCount": 1
    }
  },
  "drops": {
    "1": {
      "1004": {
        "chance": 0.2,
        "minCount": 1,
        "maxCount": 1,
        "minQuality": 6,
        "maxQuality": 7,
        "minDurability": 66,
        "maxDurability": 77,
        "item": "illarion:item_254"
      },
      "1005": {
        "chance": 0.1,
        "minCount": 1,
        "maxCount": 1,
        "minQuality": 6,
        "maxQuality": 7,
        "minDurability": 66,
        "maxDurability": 77,
        "item": "illarion:item_252"
      },
      "1006": {
        "chance": 0.01,
        "minCount": 1,
        "maxCount": 1,
        "minQuality": 6,
        "maxQuality": 7,
        "minDurability": 66,
        "maxDurability": 77,
        "item": "illarion:item_255"
      },
      "1007": {
        "chance": 0.01,
        "minCount": 1,
        "maxCount": 1,
        "minQuality": 6,
        "maxQuality": 7,
        "minDurability": 66,
        "maxDurability": 77,
        "item": "illarion:item_251"
      },
      "1008": {
        "chance": 0.01,
        "minCount": 1,
        "maxCount": 1,
        "minQuality": 6,
        "maxQuality": 7,
        "minDurability": 66,
        "maxDurability": 77,
        "item": "illarion:item_256"
      }
    },
    "2": {
      "1009": {
        "chance": 0.2,
        "minCount": 1,
        "maxCount": 1,
        "minQuality": 6,
        "maxQuality": 7,
        "minDurability": 66,
        "maxDurability": 77,
        "item": "illarion:item_46"
      },
      "1010": {
        "chance": 0.1,
        "minCount": 1,
        "maxCount": 1,
        "minQuality": 6,
        "maxQuality": 7,
        "minDurability": 66,
        "maxDurability": 77,
        "item": "illarion:item_284"
      },
      "1011": {
        "chance": 0.01,
        "minCount": 1,
        "maxCount": 1,
        "minQuality": 9,
        "maxQuality": 9,
        "minDurability": 99,
        "maxDurability": 99,
        "item": "illarion:item_3525",
        "data": {
          "gemLevel": 1
        }
      },
      "1012": {
        "chance": 0.01,
        "minCount": 1,
        "maxCount": 1,
        "minQuality": 9,
        "maxQuality": 9,
        "minDurability": 99,
        "maxDurability": 99,
        "item": "illarion:item_3524",
        "data": {
          "gemLevel": 1
        }
      },
      "1013": {
        "chance": 0.01,
        "minCount": 1,
        "maxCount": 1,
        "minQuality": 9,
        "maxQuality": 9,
        "minDurability": 99,
        "maxDurability": 99,
        "item": "illarion:item_3523",
        "data": {
          "gemLevel": 1
        }
      }
    },
    "3": {
      "1014": {
        "chance": 0.2,
        "minCount": 1,
        "maxCount": 1,
        "minQuality": 6,
        "maxQuality": 7,
        "minDurability": 66,
        "maxDurability": 77,
        "item": "illarion:item_450"
      },
      "1015": {
        "chance": 0.1,
        "minCount": 1,
        "maxCount": 1,
        "minQuality": 6,
        "maxQuality": 7,
        "minDurability": 66,
        "maxDurability": 77,
        "item": "illarion:item_279"
      },
      "1016": {
        "chance": 0.01,
        "minCount": 1,
        "maxCount": 1,
        "minQuality": 6,
        "maxQuality": 7,
        "minDurability": 66,
        "maxDurability": 77,
        "item": "illarion:item_68"
      },
      "1017": {
        "chance": 0.01,
        "minCount": 1,
        "maxCount": 1,
        "minQuality": 6,
        "maxQuality": 7,
        "minDurability": 66,
        "maxDurability": 77,
        "item": "illarion:item_278"
      },
      "1018": {
        "chance": 0.01,
        "minCount": 1,
        "maxCount": 1,
        "minQuality": 6,
        "maxQuality": 7,
        "minDurability": 66,
        "maxDurability": 77,
        "item": "illarion:item_447"
      }
    },
    "4": {
      "1019": {
        "chance": 1,
        "minCount": 10,
        "maxCount": 30,
        "minQuality": 3,
        "maxQuality": 3,
        "minDurability": 33,
        "maxDurability": 33,
        "item": "illarion:item_3077"
      }
    }
  },
  "metadata": {
    "id": 261
  }
}